{
  "done": [
    {
      "assignedTo": {
        "name": "Mazen Sharkawy"
      },
      "creation_time": "2018-11-06T12:22:13.392Z",
      "id": "2",
      "prio": 2,
      "references": [],
      "title": "git repo for the record"
    },
    {
      "assignedTo": {
        "name": "Mazen Sharkawy"
      },
      "creation_time": "2018-11-06T12:40:34.441Z",
      "id": "3",
      "prio": 2,
      "references": [],
      "title": "redirect to hompage"
    }
  ],
  "in-progress": [],
  "testing": [],
  "todo": [
    {
      "assignedTo": {
        "name": "Mazen Sharkawy"
      },
      "creation_time": "2018-11-06T13:37:12.415Z",
      "id": "7",
      "prio": 2,
      "references": [],
      "title": "customize scroll bar"
    },
    {
      "assignedTo": {
        "name": "Mazen Sharkawy"
      },
      "creation_time": "2018-11-06T13:35:55.278Z",
      "id": "4",
      "prio": 2,
      "references": [],
      "title": "Docker"
    },
    {
      "assignedTo": {
        "name": "Mazen Sharkawy"
      },
      "creation_time": "2018-11-06T13:36:14.887Z",
      "id": "5",
      "prio": 2,
      "references": [],
      "title": "Lincoln Dicision making tool"
    },
    {
      "assignedTo": {
        "name": "Mazen Sharkawy"
      },
      "creation_time": "2018-11-06T13:36:58.198Z",
      "id": "6",
      "prio": 2,
      "references": [],
      "title": "Stephen Covey's table for prioritizing"
    },
    {
      "assignedTo": {
        "name": "Mazen Sharkawy"
      },
      "creation_time": "2018-11-06T12:21:47.149Z",
      "description": {
        "content": "Push notifications when a new video is posted.\nMaybe Track unwatched videos to notify logged in users",
        "mime": "text/markdown"
      },
      "id": "1",
      "references": [],
      "title": "Push notifications"
    },
    {
      "assignedTo": {
        "name": "Mazen Sharkawy"
      },
      "creation_time": "2018-11-10T21:40:50.193Z",
      "id": "8",
      "prio": 5,
      "references": [],
      "title": "mobile first approach"
    }
  ]
}